bigtabular/__init__.py
bigtabular/_modidx.py
bigtabular/core.py
bigtabular/data.py
bigtabular/learner.py
bigtabular-0.0.3.dist-info/LICENSE
bigtabular-0.0.3.dist-info/METADATA
bigtabular-0.0.3.dist-info/WHEEL
bigtabular-0.0.3.dist-info/entry_points.txt
bigtabular-0.0.3.dist-info/top_level.txt
bigtabular-0.0.3.dist-info/RECORD
