Metadata-Version: 2.1
Name: bigtabular
Version: 0.0.3
Summary: Extension of fastai.tabular for larger-than-memory datasets with Dask
Home-page: https://github.com/stefan027/bigtabular
Author: stefan027
Author-email: stefan.strydom87@gmail.com
License: Apache Software License 2.0
Keywords: nbdev jupyter notebook python
Classifier: Development Status :: 4 - Beta
Classifier: Intended Audience :: Developers
Classifier: Natural Language :: English
Classifier: Programming Language :: Python :: 3.7
Classifier: Programming Language :: Python :: 3.8
Classifier: Programming Language :: Python :: 3.9
Classifier: Programming Language :: Python :: 3.10
Classifier: License :: OSI Approved :: Apache Software License
Requires-Python: >=3.7
License-File: LICENSE
Requires-Dist: fastcore
Requires-Dist: fastai
Requires-Dist: dask[complete]
Provides-Extra: dev
